rin_proj1/__init__.py
rin_proj1/db_insert.py
rin_proj1/get_yaml.py
rin_proj1/logerror.py
rin_proj1/main.py
rin_proj1-1.1.dist-info/METADATA
rin_proj1-1.1.dist-info/WHEEL
rin_proj1-1.1.dist-info/entry_points.txt
rin_proj1-1.1.dist-info/RECORD
