Metadata-Version: 2.1
Name: rin-proj1
Version: 1.1
Summary: CLI tool to convert .csv files to .db files and vice-versa
Author: Harine
Author-email: haariinee@gmail.com
Requires-Python: >=3.10,<4.0
Classifier: Programming Language :: Python :: 3
Classifier: Programming Language :: Python :: 3.10
Classifier: Programming Language :: Python :: 3.11
Requires-Dist: pyyaml (>=6.0,<7.0)
Requires-Dist: typer (>=0.9.0,<0.10.0)
